blockchain_csetakeoff/__init__.py
blockchain_csetakeoff/blockchain.py
blockchain_csetakeoff-0.0.1.dist-info/LICENCE
blockchain_csetakeoff-0.0.1.dist-info/METADATA
blockchain_csetakeoff-0.0.1.dist-info/WHEEL
blockchain_csetakeoff-0.0.1.dist-info/top_level.txt
blockchain_csetakeoff-0.0.1.dist-info/RECORD
