Metadata-Version: 2.1
Name: blockchain_csetakeoff
Version: 0.0.1
Summary: A prototype for illustrating how blockchain works
Author-email: cse_team_takeoff <matlab@takeoffprojects.com>
Project-URL: Homepage, https://takeoffprojects.com/
Classifier: Programming Language :: Python :: 3
Classifier: License :: OSI Approved :: MIT License
Classifier: Operating System :: OS Independent
Requires-Python: >=3.7
License-File: LICENCE
